odoo/addons/account_avatax_sale_oca/README.rst
odoo/addons/account_avatax_sale_oca/__init__.py
odoo/addons/account_avatax_sale_oca/__manifest__.py
odoo/addons/account_avatax_sale_oca/i18n/account_avatax_sale.pot
odoo/addons/account_avatax_sale_oca/i18n/account_avatax_sale_oca.pot
odoo/addons/account_avatax_sale_oca/i18n/it.po
odoo/addons/account_avatax_sale_oca/models/__init__.py
odoo/addons/account_avatax_sale_oca/models/account_move.py
odoo/addons/account_avatax_sale_oca/models/account_tax.py
odoo/addons/account_avatax_sale_oca/models/avalara_salestax.py
odoo/addons/account_avatax_sale_oca/models/sale_order.py
odoo/addons/account_avatax_sale_oca/readme/CONTRIBUTORS.md
odoo/addons/account_avatax_sale_oca/readme/DESCRIPTION.md
odoo/addons/account_avatax_sale_oca/readme/USAGE.md
odoo/addons/account_avatax_sale_oca/static/description/icon.png
odoo/addons/account_avatax_sale_oca/static/description/index.html
odoo/addons/account_avatax_sale_oca/tests/__init__.py
odoo/addons/account_avatax_sale_oca/tests/test_sale_order.py
odoo/addons/account_avatax_sale_oca/views/avalara_salestax_view.xml
odoo/addons/account_avatax_sale_oca/views/sale_order_view.xml
odoo_addon_account_avatax_sale_oca-18.0.1.0.0.4.dist-info/METADATA
odoo_addon_account_avatax_sale_oca-18.0.1.0.0.4.dist-info/WHEEL
odoo_addon_account_avatax_sale_oca-18.0.1.0.0.4.dist-info/top_level.txt
odoo_addon_account_avatax_sale_oca-18.0.1.0.0.4.dist-info/RECORD
